<?xml version="1.0" encoding ="utf-8"?><Level width="3">
<Camera x="0" y="5" minWidth="20" maxWidth="40"  />
<Birds>
<Bird type="BirdRed" />
<Bird type="BirdBlack" />
<Bird type="BirdWhite" />
</Birds>
<Slingshot x="-15" y="-2.5" />
<GameObjects>
<Block type="RectTiny" material="wood" x="7.5" y="-3.225" rotation="0" id="0"/>
<Block type="SquareHole" material="wood" x="7.5" y="-2.575" rotation="0" id="1"/>
<Block type="RectMedium" material="stone" x="7.5" y="-2.175" rotation="0" id="2"/>
<Block type="RectTiny" material="wood" x="7.5" y="-1.925" rotation="0" id="3"/>
<Block type="RectTiny" material="wood" x="7.5" y="-1.675" rotation="0" id="4"/>
<Block type="RectTiny" material="wood" x="5.0" y="-3.375" rotation="0" id="5"/>
<Block type="TriangleHole" material="wood" x="5.0" y="-2.575" rotation="0" id="6"/>
<Block type="RectTiny" material="wood" x="5.0" y="-1.925" rotation="0" id="7"/>
<Block type="RectBig" material="wood" x="5.0" y="-1.925" rotation="90" id="8"/>
<Block type="RectTiny" material="wood" x="5.0" y="-0.725" rotation="0" id="9"/>
<Block type="RectBig" material="wood" x="5.0" y="0.305" rotation="90" id="10"/>
<Block type="RectTiny" material="wood" x="5.0" y="1.105" rotation="0" id="11"/>
<Block type="SquareHole" material="wood" x="5.0" y="1.755" rotation="0" id="12"/>
<Block type="RectFat" material="wood" x="2.5" y="-2.9" rotation="0" id="13"/>
<Block type="RectTiny" material="wood" x="2.5" y="-2.25" rotation="0" id="14"/>
<Block type="RectBig" material="wood" x="2.5" y="-2.25" rotation="90" id="15"/>
<Block type="RectFat" material="wood" x="2.5" y="-1.425" rotation="0" id="16"/>
<Block type="RectMedium" material="stone" x="2.5" y="-1.075" rotation="0" id="17"/>
<Block type="RectSmall" material="wood" x="0.0" y="-2.825" rotation="0" id="18"/>
<Block type="RectBig" material="wood" x="0.0" y="-2.825" rotation="90" id="19"/>
<Block type="RectTiny" material="wood" x="0.0" y="-2.825" rotation="90" id="20"/>
<Block type="RectTiny" material="wood" x="0.0" y="-2.825" rotation="90" id="21"/>
<Block type="RectBig" material="wood" x="0.0" y="-2.825" rotation="90" id="22"/>
<Block type="TriangleHole" material="wood" x="0.0" y="-1.975" rotation="0" id="23"/>
<Block type="RectSmall" material="wood" x="-2.5" y="-3.375" rotation="0" id="24"/>
<Block type="RectBig" material="wood" x="-2.5" y="-3.125" rotation="0" id="25"/>
<Block type="RectTiny" material="wood" x="-3.4" y="-2.815" rotation="90" id="26"/>
<Block type="RectTiny" material="wood" x="-1.6" y="-2.815" rotation="90" id="27"/>
<Block type="RectBig" material="wood" x="-2.5" y="-2.505" rotation="0" id="28"/>
<Block type="RectMedium" material="stone" x="-2.5" y="-2.255" rotation="0" id="29"/>
<Block type="RectSmall" material="wood" x="-2.5" y="-1.455" rotation="0" id="30"/>
<Block type="RectBig" material="wood" x="-2.5" y="-1.455" rotation="90" id="31"/>
<Block type="RectTiny" material="wood" x="-2.5" y="-1.455" rotation="90" id="32"/>
<Block type="RectTiny" material="wood" x="-2.5" y="-1.455" rotation="90" id="33"/>
<Block type="RectBig" material="wood" x="-2.5" y="-1.455" rotation="90" id="34"/>
<Block type="SquareHole" material="wood" x="-2.5" y="-0.605" rotation="0" id="35"/>
<Block type="SquareHole" material="wood" x="-2.5" y="0.395" rotation="0" id="36"/>
<Block type="SquareSmall" material="wood" x="-2.5" y="1.045" rotation="0" id="37"/>
<Block type="RectBig" material="wood" x="-2.5" y="1.495" rotation="0" id="38"/>
<Block type="RectTiny" material="wood" x="-3.4" y="1.805" rotation="90" id="39"/>
<Block type="RectTiny" material="wood" x="-1.6" y="1.805" rotation="90" id="40"/>
<Block type="RectBig" material="wood" x="-2.5" y="2.115" rotation="0" id="41"/>
<Block type="RectTiny" material="wood" x="-2.5" y="2.365" rotation="0" id="42"/>
<Block type="RectSmall" material="wood" x="-5.0" y="-2.825" rotation="0" id="43"/>
<Block type="RectBig" material="wood" x="-5.0" y="-2.825" rotation="90" id="44"/>
<Block type="RectTiny" material="wood" x="-5.0" y="-2.825" rotation="90" id="45"/>
<Block type="RectTiny" material="wood" x="-5.0" y="-2.825" rotation="90" id="46"/>
<Block type="RectBig" material="wood" x="-5.0" y="-2.825" rotation="90" id="47"/>
<Block type="TriangleHole" material="wood" x="-5.0" y="-1.975" rotation="0" id="48"/>
<Pig type="BasicSmall" material="" x="7.5" y="-1.7" rotation="0"/>
<Pig type="BasicSmall" material="" x="5.0" y="0.93" rotation="0"/>
<Pig type="BasicSmall" material="" x="2.5" y="-1.1" rotation="0"/>
<Pig type="BasicSmall" material="" x="0.0" y="-3.4" rotation="0"/>
<Pig type="BasicSmall" material="" x="-2.5" y="2.34" rotation="0"/>
<Pig type="BasicSmall" material="" x="-5.0" y="-3.4" rotation="0"/>
<Pig type="BasicSmall" material="" x="7.5" y="-1.7" rotation="0"/>
<Pig type="BasicSmall" material="" x="5.0" y="0.93" rotation="0"/>
</GameObjects>

</Level>
